weather_swarm/__init__.py
weather_swarm/prompts.py
weather_swarm/tools/__init__.py
weather_swarm/tools/baron_tools_schema.py
weather_swarm/tools/get_geo_coordinates.py
weather_swarm/tools/tools.py
weather_swarm-0.0.7.dist-info/METADATA
weather_swarm-0.0.7.dist-info/WHEEL
weather_swarm-0.0.7.dist-info/RECORD
